fgit/__init__.py
fgit/actions.py
fgit/utils/__init__.py
fgit/utils/git.py
fgit/utils/message_box.py
fgit_cli/__init__.py
fgit_cli/main.py
fgit-0.0.1b8.dist-info/LICENSE
fgit-0.0.1b8.dist-info/METADATA
fgit-0.0.1b8.dist-info/WHEEL
fgit-0.0.1b8.dist-info/entry_points.txt
fgit-0.0.1b8.dist-info/top_level.txt
fgit-0.0.1b8.dist-info/RECORD
